vsiew/__init__.py
vsiew/__main__.py
vsiew/_metadata.py
vsiew/init.py
vsiew-2.3.8.dist-info/LICENSE
vsiew-2.3.8.dist-info/METADATA
vsiew-2.3.8.dist-info/WHEEL
vsiew-2.3.8.dist-info/entry_points.txt
vsiew-2.3.8.dist-info/top_level.txt
vsiew-2.3.8.dist-info/RECORD
